hypermanager/decorators.py
hypermanager/events.py
hypermanager/helpers.py
hypermanager/manager.py
hypermanager/networks.py
hypermanager/schema.py
hypermanager/protocols/across.py
hypermanager/protocols/mev_commit.py
hypermanager/protocols/uniswap_v3.py
hypermanager-0.1.12.dist-info/METADATA
hypermanager-0.1.12.dist-info/WHEEL
hypermanager-0.1.12.dist-info/RECORD
